MANIFEST.in
board_crm_view.xml
crm_action_rule_demo.xml
crm_data.xml
crm_demo.xml
crm_lead_data.xml
crm_lead_demo.xml
crm_lead_menu.xml
crm_lead_view.xml
crm_meeting_menu.xml
crm_phonecall_data.xml
crm_phonecall_demo.xml
crm_phonecall_menu.xml
crm_phonecall_view.xml
crm_report.xml
crm_report_view.xml
crm_view.xml
res_config_view.xml
res_partner_view.xml
setup.py
./__init__.py
./__openerp__.py
./crm.py
./crm_lead.py
./crm_meeting.py
./crm_phonecall.py
./crm_segmentation.py
./res_config.py
./res_partner.py
./report/__init__.py
./report/crm_lead_report.py
./report/crm_phonecall_report.py
./report/report_businessopp.py
./wizard/__init__.py
./wizard/crm_lead_to_opportunity.py
./wizard/crm_merge_opportunities.py
./wizard/crm_opportunity_to_phonecall.py
./wizard/crm_partner_binding.py
./wizard/crm_phonecall_to_meeting.py
./wizard/crm_phonecall_to_opportunity.py
./wizard/crm_phonecall_to_phonecall.py
i18n/ar.po
i18n/bg.po
i18n/bs.po
i18n/ca.po
i18n/crm.pot
i18n/cs.po
i18n/da.po
i18n/de.po
i18n/el.po
i18n/es.po
i18n/es_AR.po
i18n/es_CR.po
i18n/es_EC.po
i18n/es_MX.po
i18n/es_PY.po
i18n/es_VE.po
i18n/et.po
i18n/fi.po
i18n/fr.po
i18n/gl.po
i18n/gu.po
i18n/he.po
i18n/hr.po
i18n/hu.po
i18n/id.po
i18n/it.po
i18n/ja.po
i18n/ko.po
i18n/lo.po
i18n/lt.po
i18n/lv.po
i18n/mk.po
i18n/mn.po
i18n/nb.po
i18n/nl.po
i18n/nl_BE.po
i18n/pl.po
i18n/pt.po
i18n/pt_BR.po
i18n/ro.po
i18n/ru.po
i18n/sk.po
i18n/sl.po
i18n/sq.po
i18n/sr.po
i18n/sr@latin.po
i18n/sv.po
i18n/th.po
i18n/tlh.po
i18n/tr.po
i18n/uk.po
i18n/vi.po
i18n/zh_CN.po
i18n/zh_TW.po
images/crm_dashboard.png
images/customers.png
images/leads.png
images/logged_calls.png
images/opportunities_calendar.png
images/opportunities_form.png
images/opportunities_graph.png
images/opportunities_kanban.png
images/scheduled_calls.png
images/stages.png
openerp_crm.egg-info/PKG-INFO
openerp_crm.egg-info/SOURCES.txt
openerp_crm.egg-info/dependency_links.txt
openerp_crm.egg-info/requires.txt
openerp_crm.egg-info/top_level.txt
process/crm_configuration_process.xml
report/crm_lead_report_view.xml
report/crm_phonecall_report_view.xml
security/crm_security.xml
security/ir.model.access.csv
static/src/img/icon.png
